micropipes/shared/__init__.py
micropipes/shared/constants.py
micropipes/shared/constants_runtime.py
micropipes/shared/constants_stats_names.py
micropipes/shared/job.py
micropipes/shared/job.schema.json
micropipes/shared/namegen.py
micropipes/shared/shared_files.py
micropipes/shared/utils.py
micropipes/workers/__init__.py
micropipes/workers/runtime.py
micropipes/workers/worker.py
micropipes_worker-0.0.70.dist-info/METADATA
micropipes_worker-0.0.70.dist-info/WHEEL
micropipes_worker-0.0.70.dist-info/top_level.txt
micropipes_worker-0.0.70.dist-info/RECORD
