Metadata-Version: 2.1
Name: micropipes-worker
Version: 0.0.70
Summary: Micropipes worker package
Home-page: https://gitlab.com/aicu/lab/aicu_micropipes
Author: Richard Holly
Author-email: richard.holly@optimaideas.com
License: Commercial
Platform: UNKNOWN
Requires-Dist: jsonschema (>=3.0.1)
Requires-Dist: pika (>=1.0.0)
